typetest/__init__.py
typetest/__main__.py
typetest/analyse/__init__.py
typetest/analyse/__main__.py
typetest/analyse/mistyped_words_pie_chart.py
typetest/analyse/typing_speed_distribution.py
typetest/analyse/typing_speed_of_n_best_words.py
typetest/analyse/typing_speed_per_char.py
typetest/analyse/typing_speed_per_test.py
typetest/analyse/typing_speed_per_test_duration.py
typetest/results/placeholder
typetest/tests/common_1000
typetest/tests/common_300
typetest/tests/no_double_letters
typetest/utils.py
typetest-0.1.9.dist-info/entry_points.txt
typetest-0.1.9.dist-info/LICENSE
typetest-0.1.9.dist-info/WHEEL
typetest-0.1.9.dist-info/METADATA
typetest-0.1.9.dist-info/RECORD
