Metadata-Version: 2.1
Name: typetest
Version: 0.1.9
Summary: Test your typing speed without leaving the terminal.
Home-page: https://github.com/MasterMedo/typetest
License: MIT
Keywords: typing,test,wpm,speed,terminal
Author: MasterMedo
Author-email: mislav.vuletic@gmail.com
Maintainer: MasterMedo
Maintainer-email: mislav.vuletic@gmail.com
Requires-Python: >=3.9,<4.0
Classifier: License :: OSI Approved :: MIT License
Classifier: Programming Language :: Python :: 3
Classifier: Programming Language :: Python :: 3.10
Classifier: Programming Language :: Python :: 3.9
Requires-Dist: blessed (>=1.18.1,<2.0.0)
Requires-Dist: matplotlib (>=3.4.2,<4.0.0)
Requires-Dist: pandas (>=1.3.0,<2.0.0)
Requires-Dist: seaborn (>=0.11.1,<0.12.0)
Project-URL: Documentation, https://github.com/MasterMedo/typetest
Project-URL: Repository, https://github.com/MasterMedo/typetest
